LICENSE.txt
MANIFEST.in
README.md
requirements.txt
setup.py
version.txt
impala_shell/ImpalaHttpClient.py
impala_shell/TSSLSocketWithWildcardSAN.py
impala_shell/__init__.py
impala_shell/compatibility.py
impala_shell/cookie_util.py
impala_shell/impala_build_version.py
impala_shell/impala_client.py
impala_shell/impala_shell.py
impala_shell/impala_shell_config_defaults.py
impala_shell/option_parser.py
impala_shell/shell_exceptions.py
impala_shell/shell_output.py
impala_shell/value_converter.py
impala_shell.egg-info/PKG-INFO
impala_shell.egg-info/SOURCES.txt
impala_shell.egg-info/dependency_links.txt
impala_shell.egg-info/entry_points.txt
impala_shell.egg-info/requires.txt
impala_shell.egg-info/top_level.txt
impala_shell/BackendGflags/__init__.py
impala_shell/BackendGflags/constants.py
impala_shell/BackendGflags/ttypes.py
impala_shell/CatalogInternalService/__init__.py
impala_shell/CatalogInternalService/constants.py
impala_shell/CatalogInternalService/ttypes.py
impala_shell/CatalogObjects/__init__.py
impala_shell/CatalogObjects/constants.py
impala_shell/CatalogObjects/ttypes.py
impala_shell/CatalogService/CatalogService.py
impala_shell/CatalogService/__init__.py
impala_shell/CatalogService/constants.py
impala_shell/CatalogService/ttypes.py
impala_shell/Data/__init__.py
impala_shell/Data/constants.py
impala_shell/Data/ttypes.py
impala_shell/DataSinks/__init__.py
impala_shell/DataSinks/constants.py
impala_shell/DataSinks/ttypes.py
impala_shell/Descriptors/__init__.py
impala_shell/Descriptors/constants.py
impala_shell/Descriptors/ttypes.py
impala_shell/ErrorCodes/__init__.py
impala_shell/ErrorCodes/constants.py
impala_shell/ErrorCodes/ttypes.py
impala_shell/ExecStats/__init__.py
impala_shell/ExecStats/constants.py
impala_shell/ExecStats/ttypes.py
impala_shell/Exprs/__init__.py
impala_shell/Exprs/constants.py
impala_shell/Exprs/ttypes.py
impala_shell/ExternalDataSource/__init__.py
impala_shell/ExternalDataSource/constants.py
impala_shell/ExternalDataSource/ttypes.py
impala_shell/Frontend/__init__.py
impala_shell/Frontend/constants.py
impala_shell/Frontend/ttypes.py
impala_shell/ImpalaInternalService/__init__.py
impala_shell/ImpalaInternalService/constants.py
